LICENSE
README.md
pyproject.toml
setup.py
py_import_cycles/__init__.py
py_import_cycles/__main__.py
py_import_cycles/cli.py
py_import_cycles/cycles.py
py_import_cycles/dfs.py
py_import_cycles/files.py
py_import_cycles/graphs.py
py_import_cycles/johnson.py
py_import_cycles/log.py
py_import_cycles/modules.py
py_import_cycles/tarjan.py
py_import_cycles/type_defs.py
py_import_cycles/visitors.py
py_import_cycles.egg-info/PKG-INFO
py_import_cycles.egg-info/SOURCES.txt
py_import_cycles.egg-info/dependency_links.txt
py_import_cycles.egg-info/entry_points.txt
py_import_cycles.egg-info/requires.txt
py_import_cycles.egg-info/top_level.txt