Metadata-Version: 2.1
Name: py-import-cycles
Version: 0.3.0
Summary: Detect import cycles in Python projects
Home-page: https://github.com/si-23/py-import-cycles
Author: Simon Jess
Author-email: simon86betz@yahoo.de
License: MIT
Classifier: License :: OSI Approved :: MIT License
Classifier: Programming Language :: Python :: 3
Classifier: Programming Language :: Python :: 3.10
Classifier: Programming Language :: Python :: 3.12
License-File: LICENSE
Requires-Dist: graphviz
Requires-Dist: networkx
